LICENSE
MANIFEST.in
README
setup.py
calloway/__init__.py
calloway/default_settings.py
calloway/menu.py
calloway/settings.py
calloway/urls.py
calloway.egg-info/PKG-INFO
calloway.egg-info/SOURCES.txt
calloway.egg-info/dependency_links.txt
calloway.egg-info/top_level.txt
calloway/apps/api/__init__.py
calloway/apps/api/handlers.py
calloway/apps/api/urls.py
calloway/apps/custom_registration/__init__.py
calloway/apps/custom_registration/backends/__init__.py
calloway/apps/custom_registration/backends/email/__init__.py
calloway/apps/custom_registration/backends/email/forms.py
calloway/apps/custom_registration/backends/email/urls.py
calloway/apps/custom_registration/management/__init__.py
calloway/apps/custom_registration/management/commands/__init__.py
calloway/apps/custom_registration/management/commands/check_expired_accounts.py
calloway/apps/custom_registration/templates/registration/email/emails/account_expired.txt
calloway/apps/custom_registration/templates/registration/email/emails/account_expired_subject.txt
calloway/apps/custom_registration/templates/registration/email/emails/password.txt
calloway/apps/custom_registration/templates/registration/email/emails/password_subject.txt
calloway/apps/django_ext/__init__.py
calloway/apps/django_ext/cache.py
calloway/apps/django_ext/caseinsensitiveauth.py
calloway/apps/django_ext/fields.py
calloway/apps/django_ext/managers.py
calloway/apps/django_ext/markov.py
calloway/apps/django_ext/models.py
calloway/apps/django_ext/views.py
calloway/apps/django_ext/fixtures/demo_categories.txt
calloway/apps/django_ext/fixtures/demo_story_data.txt
calloway/apps/django_ext/management/__init__.py
calloway/apps/django_ext/management/commands/__init__.py
calloway/apps/django_ext/management/commands/create_demo_data.py
calloway/apps/django_ext/management/commands/delete_contenttypes.py
calloway/apps/django_ext/management/commands/e2c.py
calloway/apps/django_ext/management/commands/flush_all_memcached.py
calloway/apps/django_ext/management/commands/generate_reqs.py
calloway/apps/django_ext/middleware/__init__.py
calloway/apps/django_ext/middleware/cookie.py
